eric_chen_forward/database.py
eric_chen_forward/model.py
eric_chen_forward/url_classifier_demo.py
eric_chen_forward/util.py
eric_chen_forward-0.0.12.dist-info/METADATA
eric_chen_forward-0.0.12.dist-info/WHEEL
eric_chen_forward-0.0.12.dist-info/licenses/LICENSE
eric_chen_forward-0.0.12.dist-info/RECORD
