Metadata-Version: 2.1
Name: eric_chen_forward
Version: 0.0.12
Summary: Classifier for institution and scholar data
Project-URL: Homepage, https://github.com/ezrc2/eric_chen_forward
Author-email: Eric Chen <ezchen2556@gmail.com>
License-File: LICENSE
Classifier: License :: OSI Approved :: MIT License
Classifier: Operating System :: OS Independent
Classifier: Programming Language :: Python :: 3
Requires-Python: >=3.7
Requires-Dist: beautifulsoup4>=4.11.1
Requires-Dist: lxml>=4.9.1
Requires-Dist: nltk>=3.7
Requires-Dist: numpy>=1.23.3
Requires-Dist: pandas>=1.5.0
Requires-Dist: scikit-learn>=1.1.2
Requires-Dist: spacy-legacy>=3.0.10
Requires-Dist: spacy-loggers>=1.0.3
Requires-Dist: spacy>=3.4.1
Requires-Dist: streamlit>=1.12.2
Requires-Dist: torch>=1.13.1
Requires-Dist: trafilatura>=1.3.0
Requires-Dist: transformers>=4.26.1
Requires-Dist: watchdog>=2.1.9
